AUTHORS
LICENSE
MANIFEST.in
README.rst
setup.py
django_storelocator.egg-info/PKG-INFO
django_storelocator.egg-info/SOURCES.txt
django_storelocator.egg-info/dependency_links.txt
django_storelocator.egg-info/not-zip-safe
django_storelocator.egg-info/requires.txt
django_storelocator.egg-info/top_level.txt
storelocator/__init__.py
storelocator/admin.py
storelocator/factories.py
storelocator/forms.py
storelocator/models.py
storelocator/urls.py
storelocator/utils.py
storelocator/views.py
storelocator/importers/__init__.py
storelocator/importers/importer.py
storelocator/importers/locations.py
storelocator/importers/shops.py
storelocator/locale/nl/LC_MESSAGES/django.mo
storelocator/locale/nl/LC_MESSAGES/django.po
storelocator/management/__init__.py
storelocator/management/commands/__init__.py
storelocator/management/commands/import_locations.py
storelocator/management/commands/import_shops.py
storelocator/management/commands/update_locations.py
storelocator/management/commands/update_shops.py
storelocator/migrations/0001_initial.py
storelocator/migrations/__init__.py
storelocator/tests/__init__.py
storelocator/tests/test_forms.py
storelocator/tests/test_importers.py
storelocator/tests/test_utils.py
storelocator/tests/test_views.py
storelocator/tests/testcase.py
storelocator/tests/testsettings.py
storelocator/tests/testdata/testlocations.csv
storelocator/tests/testdata/testshops.csv
storelocator/updaters/__init__.py
storelocator/updaters/google.py
storelocator/updaters/yahoo.py